bareqr/__init__.py
bareqr/corr.py
bareqr/data.py
bareqr/extra.py
bareqr/mask.py
bareqr/qr.py
bareqr/util.py
bareqr-0.1.1.dist-info/licenses/LICENSE
bareqr-0.1.1.dist-info/WHEEL
bareqr-0.1.1.dist-info/METADATA
bareqr-0.1.1.dist-info/RECORD
