Metadata-Version: 2.4
Name: bareqr
Version: 0.1.1
Summary: Bare headless QR code generator
Author: jkmnt
Requires-Python: >=3.12
Classifier: Programming Language :: Python :: 3
Classifier: License :: OSI Approved :: MIT License
Classifier: Operating System :: OS Independent
License-File: LICENSE
Project-URL: Documentation, https://jkmnt.github.com/bareqr
Project-URL: Source, https://github.com/jkmnt/bareqr
